{"appid":"16109046","compilation-args":{"options":[],"selected":-1},"editor":{"curPath":"D:\\12-baidu-project\\房地产经纪人\\房地产经纪人\\pages\\esoterica\\esoterica.js","expands":["D:\\12-baidu-project\\房地产经纪人\\房地产经纪人\\components","D:\\12-baidu-project\\房地产经纪人\\房地产经纪人\\pages","D:\\12-baidu-project\\房地产经纪人\\房地产经纪人\\pages\\tiku","D:\\12-baidu-project\\房地产经纪人\\房地产经纪人\\common","D:\\12-baidu-project\\房地产经纪人\\房地产经纪人\\pages\\mine\\mineIndex","D:\\12-baidu-project\\房地产经纪人\\房地产经纪人\\pages\\index","D:\\12-baidu-project\\房地产经纪人\\房地产经纪人\\pages\\tiku\\zuoti","D:\\12-baidu-project\\房地产经纪人\\房地产经纪人\\pages\\tiku\\wrong","D:\\12-baidu-project\\房地产经纪人\\房地产经纪人\\pages\\tiku\\mark","D:\\12-baidu-project\\房地产经纪人\\房地产经纪人\\pages\\tiku\\modelReal","D:\\12-baidu-project\\房地产经纪人\\房地产经纪人\\pages\\tiku\\modelReal\\modelRealDetail","D:\\12-baidu-project\\房地产经纪人\\房地产经纪人\\components\\question","D:\\12-baidu-project\\房地产经纪人\\房地产经纪人\\pages\\tiku\\modelTest","D:\\12-baidu-project\\房地产经纪人\\房地产经纪人\\pages\\prompt","D:\\12-baidu-project\\房地产经纪人\\房地产经纪人\\pages\\prompt\\modelRealScore","D:\\12-baidu-project\\房地产经纪人\\房地产经纪人\\pages\\esoterica","D:\\12-baidu-project\\房地产经纪人\\房地产经纪人\\pages\\kaodianDetail"],"paths":["D:\\12-baidu-project\\房地产经纪人\\房地产经纪人\\pages\\esoterica\\esoterica.js","D:\\12-baidu-project\\房地产经纪人\\房地产经纪人\\common\\validate.js","D:\\12-baidu-project\\房地产经纪人\\房地产经纪人\\pages\\tiku\\modelReal\\modelRealDetail\\modelRealDetail.js","D:\\12-baidu-project\\房地产经纪人\\房地产经纪人\\pages\\tiku\\modelReal\\modelRealDetail\\modelRealDetail.swan","D:\\12-baidu-project\\房地产经纪人\\房地产经纪人\\pages\\tiku\\wrong\\wrong.swan","D:\\12-baidu-project\\房地产经纪人\\房地产经纪人\\pages\\tiku\\zuoti\\zuoti.swan","D:\\12-baidu-project\\房地产经纪人\\房地产经纪人\\pages\\tiku\\mark\\mark.swan","D:\\12-baidu-project\\房地产经纪人\\房地产经纪人\\pages\\prompt\\modelRealScore\\modelRealScore.js","D:\\12-baidu-project\\房地产经纪人\\房地产经纪人\\app.js"]},"host":"baiduboxapp","preview":{"packageId":101133},"publish":{"version":"1.7"},"setting":{"urlCheck":true},"swan":{"baiduboxapp":{"extensionJsVersion":"","swanJsVersion":"3.30.31"}}}